Day5/Sequential_circuits/mod5_counter/mod5_counter.v
module mod5_counter(
    input CLK,
    output reg [2:0] Q0
);

initial
begin
    Q0 = 3'b000;
end

always @(posedge CLK)
begin
    if(Q0 == 3'd4)
        Q0 <= 3'd0;
    else
        Q0 <= Q0 + 1;
end

endmodule

Day5/Sequential_circuits/mod5_counter/mod5_countertb.v
module mod5_countertb;

reg CLK;
wire [2:0] Q0;

mod5_counter uut(
    .CLK(CLK),
    .Q0(Q0)
);

always
begin
    #5 CLK = ~CLK;
end

initial
begin
    $dumpfile("wave.vcd");
    $dumpvars(0, uut);

    CLK = 0;

    $display("Time\tCLK\tQ0");
    $monitor("%0t\t%b\t%b",$time,CLK,Q0);

    #120;
    $finish;
end

endmodule

Day5/Sequential_circuits/mod5_counter/wave.vcd
$date
	Tue Jul 21 12:21:17 2026
$end
$version
	Icarus Verilog
$end
$timescale
	1s
$end
$scope module mod5_countertb $end
$scope module uut $end
$var wire 1 ! CLK $end
$var reg 3 " Q0 [2:0] $end
$upscope $end
$upscope $end
$enddefinitions $end
$comment Show the parameter values. $end
$dumpall
$end
#0
$dumpvars
b0 "
0!
$end
#5
b1 "
1!
#10
0!
#15
b10 "
1!
#20
0!
#25
b11 "
1!
#30
0!
#35
b100 "
1!
#40
0!
#45
b0 "
1!
#50
0!
#55
b1 "
1!
#60
0!
#65
b10 "
1!
#70
0!
#75
b11 "
1!
#80
0!
#85
b100 "
1!
#90
0!
#95
b0 "
1!
#100
0!
#105
b1 "
1!
#110
0!
#115
b10 "
1!
