Day5/Sequential_circuits/ring_counter/ring_counter.v
module ring_counter(
    input CLK,
    output reg [3:0] Q0
);

initial
begin
    Q0 = 4'b0001;
end

always @(posedge CLK)
begin
    Q0 <= {Q0[2:0], Q0[3]};
end

endmodule

Day5/Sequential_circuits/ring_counter/ring_countertb.v
module ring_countertb;

reg CLK;
wire [3:0] Q0;

ring_counter uut(
    .CLK(CLK),
    .Q0(Q0)
);

always
begin
    #5 CLK = ~CLK;
end

initial
begin
    $dumpfile("wave.vcd");
    $dumpvars(0, uut);

    CLK = 0;

    $display("Time\tCLK\tQ0");
    $monitor("%0t\t%b\t%b", $time, CLK, Q0);

    #100;
    $finish;
end

endmodule

Day5/Sequential_circuits/ring_counter/wave.vcd
$date
	Tue Jul 21 12:25:48 2026
$end
$version
	Icarus Verilog
$end
$timescale
	1s
$end
$scope module ring_countertb $end
$scope module uut $end
$var wire 1 ! CLK $end
$var reg 4 " Q0 [3:0] $end
$upscope $end
$upscope $end
$enddefinitions $end
$comment Show the parameter values. $end
$dumpall
$end
#0
$dumpvars
b1 "
0!
$end
#5
b10 "
1!
#10
0!
#15
b100 "
1!
#20
0!
#25
b1000 "
1!
#30
0!
#35
b1 "
1!
#40
0!
#45
b10 "
1!
#50
0!
#55
b100 "
1!
#60
0!
#65
b1000 "
1!
#70
0!
#75
b1 "
1!
#80
0!
#85
b10 "
1!
#90
0!
#95
b100 "
1!
