Day2/gray_to_binary/gray_to_binary.v
module gray_to_binary(input [3:0] gray,output [3:0] binary);

   wire w1, w2, w3;

   buf(binary[3], gray[3]);


   xor(w1, gray[3], gray[2]);
   buf(binary[2], w1);
   xor(w2, w1, gray[1]);
   buf(binary[1], w2);
   xor(w3, w2, gray[0]);
   buf(binary[0], w3);

endmodule

Day2/gray_to_binary/gray_to_binarytb.v
module gray_to_binarytb;

reg  [3:0] gray;
wire [3:0] binary;

gray_to_binary uut (
    .gray(gray),
    .binary(binary)
);

initial
begin
    $dumpfile("gray_to_binary.vcd");
    $dumpvars(0, gray_to_binarytb);

    $display("------------------------");
    $display(" Gray | Binary");
    $display("------------------------");

    gray = 4'b0000; #10; $display(" %b | %b", gray, binary);
    gray = 4'b0001; #10; $display(" %b | %b", gray, binary);
    gray = 4'b0011; #10; $display(" %b | %b", gray, binary);
    gray = 4'b0010; #10; $display(" %b | %b", gray, binary);
    gray = 4'b0110; #10; $display(" %b | %b", gray, binary);
    gray = 4'b0111; #10; $display(" %b | %b", gray, binary);
    gray = 4'b0101; #10; $display(" %b | %b", gray, binary);
    gray = 4'b0100; #10; $display(" %b | %b", gray, binary);
    gray = 4'b1100; #10; $display(" %b | %b", gray, binary);
    gray = 4'b1101; #10; $display(" %b | %b", gray, binary);
    gray = 4'b1111; #10; $display(" %b | %b", gray, binary);
    gray = 4'b1110; #10; $display(" %b | %b", gray, binary);
    gray = 4'b1010; #10; $display(" %b | %b", gray, binary);
    gray = 4'b1011; #10; $display(" %b | %b", gray, binary);
    gray = 4'b1001; #10; $display(" %b | %b", gray, binary);
    gray = 4'b1000; #10; $display(" %b | %b", gray, binary);

    $finish;
end

endmodule

Day2/gray_to_binary/gray_to_binary.vcd
$date
	Sat Jul 18 05:32:47 2026
$end
$version
	Icarus Verilog
$end
$timescale
	1s
$end
$scope module gray_to_binarytb $end
$var wire 4 ! binary [3:0] $end
$var reg 4 " gray [3:0] $end
$scope module uut $end
$var wire 4 # gray [3:0] $end
$var wire 1 $ w1 $end
$var wire 1 % w2 $end
$var wire 1 & w3 $end
$var wire 4 ' binary [3:0] $end
$upscope $end
$upscope $end
$enddefinitions $end
$comment Show the parameter values. $end
$dumpall
$end
#0
$dumpvars
b0 '
0&
0%
0$
b0 #
b0 "
b0 !
$end
#10
b1 !
b1 '
1&
b1 "
b1 #
#20
b10 !
b10 '
0&
1%
b11 "
b11 #
#30
b11 !
b11 '
1&
b10 "
b10 #
#40
0&
b100 !
b100 '
0%
1$
b110 "
b110 #
#50
b101 !
b101 '
1&
b111 "
b111 #
#60
b110 !
b110 '
0&
1%
b101 "
b101 #
#70
b111 !
b111 '
1&
b100 "
b100 #
#80
0&
0%
b1000 !
b1000 '
0$
b1100 "
b1100 #
#90
b1001 !
b1001 '
1&
b1101 "
b1101 #
#100
b1010 !
b1010 '
0&
1%
b1111 "
b1111 #
#110
b1011 !
b1011 '
1&
b1110 "
b1110 #
#120
0&
b1100 !
b1100 '
0%
1$
b1010 "
b1010 #
#130
b1101 !
b1101 '
1&
b1011 "
b1011 #
#140
b1110 !
b1110 '
0&
1%
b1001 "
b1001 #
#150
b1111 !
b1111 '
1&
b1000 "
b1000 #
