Day2/binary_to_gray/binary_to_gray.v
module binary_to_gray(
    input  [3:0] B,
    output [3:0] G
);

    
    buf (G[3], B[3]);

    
    xor (G[2], B[3], B[2]);
    xor (G[1], B[2], B[1]);
    xor (G[0], B[1], B[0]);

endmodule

Day2/binary_to_gray/binary_to_graytb.v
module binary_to_graytb;

    reg  [3:0] B;
    wire [3:0] G;

    
    binary_to_gray uut (
        .B(B),
        .G(G)
    );

    initial begin

        $dumpfile("binary_to_gray.vcd");
        $dumpvars(0, binary_to_graytb);

        $display(" Binary | Gray ");
        $display("----------------");

        B = 4'b0000; #10; $display("  %b   | %b", B, G);
        B = 4'b0001; #10; $display("  %b   | %b", B, G);
        B = 4'b0010; #10; $display("  %b   | %b", B, G);
        B = 4'b0011; #10; $display("  %b   | %b", B, G);
        B = 4'b0100; #10; $display("  %b   | %b", B, G);
        B = 4'b0101; #10; $display("  %b   | %b", B, G);
        B = 4'b0110; #10; $display("  %b   | %b", B, G);
        B = 4'b0111; #10; $display("  %b   | %b", B, G);
        B = 4'b1000; #10; $display("  %b   | %b", B, G);
        B = 4'b1001; #10; $display("  %b   | %b", B, G);
        B = 4'b1010; #10; $display("  %b   | %b", B, G);
        B = 4'b1011; #10; $display("  %b   | %b", B, G);
        B = 4'b1100; #10; $display("  %b   | %b", B, G);
        B = 4'b1101; #10; $display("  %b   | %b", B, G);
        B = 4'b1110; #10; $display("  %b   | %b", B, G);
        B = 4'b1111; #10; $display("  %b   | %b", B, G);

        $finish;

    end

endmodule

Day2/binary_to_gray/binary_to_gray.vcd
$date
	Sat Jul 18 05:10:48 2026
$end
$version
	Icarus Verilog
$end
$timescale
	1s
$end
$scope module binary_to_graytb $end
$var wire 4 ! G [3:0] $end
$var reg 4 " B [3:0] $end
$scope module uut $end
$var wire 4 # B [3:0] $end
$var wire 4 $ G [3:0] $end
$upscope $end
$upscope $end
$enddefinitions $end
$comment Show the parameter values. $end
$dumpall
$end
#0
$dumpvars
b0 $
b0 #
b0 "
b0 !
$end
#10
b1 !
b1 $
b1 "
b1 #
#20
b11 !
b11 $
b10 "
b10 #
#30
b10 !
b10 $
b11 "
b11 #
#40
b110 !
b110 $
b100 "
b100 #
#50
b111 !
b111 $
b101 "
b101 #
#60
b101 !
b101 $
b110 "
b110 #
#70
b100 !
b100 $
b111 "
b111 #
#80
b1100 !
b1100 $
b1000 "
b1000 #
#90
b1101 !
b1101 $
b1001 "
b1001 #
#100
b1111 !
b1111 $
b1010 "
b1010 #
#110
b1110 !
b1110 $
b1011 "
b1011 #
#120
b1010 !
b1010 $
b1100 "
b1100 #
#130
b1011 !
b1011 $
b1101 "
b1101 #
#140
b1001 !
b1001 $
b1110 "
b1110 #
#150
b1000 !
b1000 $
b1111 "
b1111 #
