Day5/Sequential_circuits/up_down_counter/up_down_counter.v
module up_down_counter(
    input CLK,
    input U_D,
    output reg [3:0] Q0
);

initial
begin
    Q0 = 4'b0000;
end

always @(posedge CLK)
begin
    if(U_D)
        Q0 <= Q0 + 1;
    else
        Q0 <= Q0 - 1;
end

endmodule

Day5/Sequential_circuits/up_down_counter/up_down_countertb.v
module up_down_countertb;

reg CLK;
reg U_D;

wire [3:0] Q0;

up_down_counter uut(
    .CLK(CLK),
    .U_D(U_D),
    .Q0(Q0)
);

always
begin
    #5 CLK = ~CLK;
end

initial
begin
    $dumpfile("wave.vcd");
    $dumpvars(0, uut);

    CLK = 0;
    U_D = 1;

    $display("Time\tCLK\tU_D\tQ0");
    $monitor("%0t\t%b\t%b\t%b",$time,CLK,U_D,Q0);

    #80 U_D = 0;
    #80 U_D = 1;

    #40;
    $finish;
end

endmodule

Day5/Sequential_circuits/up_down_counter/wave.vcd
$date
	Tue Jul 21 12:13:58 2026
$end
$version
	Icarus Verilog
$end
$timescale
	1s
$end
$scope module up_down_countertb $end
$scope module uut $end
$var wire 1 ! CLK $end
$var wire 1 " U_D $end
$var reg 4 # Q0 [3:0] $end
$upscope $end
$upscope $end
$enddefinitions $end
$comment Show the parameter values. $end
$dumpall
$end
#0
$dumpvars
b0 #
1"
0!
$end
#5
b1 #
1!
#10
0!
#15
b10 #
1!
#20
0!
#25
b11 #
1!
#30
0!
#35
b100 #
1!
#40
0!
#45
b101 #
1!
#50
0!
#55
b110 #
1!
#60
0!
#65
b111 #
1!
#70
0!
#75
b1000 #
1!
#80
0!
0"
#85
b111 #
1!
#90
0!
#95
b110 #
1!
#100
0!
#105
b101 #
1!
#110
0!
#115
b100 #
1!
#120
0!
#125
b11 #
1!
#130
0!
#135
b10 #
1!
#140
0!
#145
b1 #
1!
#150
0!
#155
b0 #
1!
#160
0!
1"
#165
b1 #
1!
#170
0!
#175
b10 #
1!
#180
0!
#185
b11 #
1!
#190
0!
#195
b100 #
1!
