Day5/Sequential_circuits/4bit_up_counter/up_counter_4bit.v
module up_counter_4bit(
    input CLK,
    output reg [3:0] Q0
);

initial
begin
    Q0 = 4'b0000;
end

always @(posedge CLK)
begin
    Q0 <= Q0 + 1;
end

endmodule

Day5/Sequential_circuits/4bit_up_counter/up_counter_4bittb.v
module up_counter_4bittb;

reg CLK;
wire [3:0] Q0;

up_counter_4bit uut(
    .CLK(CLK),
    .Q0(Q0)
);

always
begin
    #5 CLK = ~CLK;
end

initial
begin
    $dumpfile("wave.vcd");
    $dumpvars(0, uut);

    CLK = 0;

    $display("Time\tCLK\tQ0");
    $monitor("%0t\t%b\t%b",$time,CLK,Q0);

    #170;
    $finish;
end

endmodule

Day5/Sequential_circuits/4bit_up_counter/wave.vcd
$date
	Tue Jul 21 12:08:55 2026
$end
$version
	Icarus Verilog
$end
$timescale
	1s
$end
$scope module up_counter_4bittb $end
$scope module uut $end
$var wire 1 ! CLK $end
$var reg 4 " Q0 [3:0] $end
$upscope $end
$upscope $end
$enddefinitions $end
$comment Show the parameter values. $end
$dumpall
$end
#0
$dumpvars
b0 "
0!
$end
#5
b1 "
1!
#10
0!
#15
b10 "
1!
#20
0!
#25
b11 "
1!
#30
0!
#35
b100 "
1!
#40
0!
#45
b101 "
1!
#50
0!
#55
b110 "
1!
#60
0!
#65
b111 "
1!
#70
0!
#75
b1000 "
1!
#80
0!
#85
b1001 "
1!
#90
0!
#95
b1010 "
1!
#100
0!
#105
b1011 "
1!
#110
0!
#115
b1100 "
1!
#120
0!
#125
b1101 "
1!
#130
0!
#135
b1110 "
1!
#140
0!
#145
b1111 "
1!
#150
0!
#155
b0 "
1!
#160
0!
#165
b1 "
1!
