Day2/comparator/comp.v
module comp(
    input [1:0] A,
    input [1:0] B,
    output GT,
    output LT,
    output EQ
);

    wire nA1, nA0, nB1, nB0;
    wire eq1, eq0;
    wire gt1, gt0;
    wire lt1, lt0;
    wire wgt, wlt;

    
    not (nA1, A[1]);
    not (nA0, A[0]);
    not (nB1, B[1]);
    not (nB0, B[0]);

    
    xnor (eq1, A[1], B[1]);
    xnor (eq0, A[0], B[0]);

   
    and (gt1, A[1], nB1);
    and (gt0, A[0], nB0);
    and (wgt, eq1, gt0);
    or  (GT, gt1, wgt);

    
    and (lt1, nA1, B[1]);
    and (lt0, nA0, B[0]);
    and (wlt, eq1, lt0);
    or  (LT, lt1, wlt);

   
    and (EQ, eq1, eq0);

endmodule

Day2/comparator/comptb.v
module comptb;

    reg [1:0] A;
    reg [1:0] B;

    wire GT;
    wire LT;
    wire EQ;

    
    comp uut (
        .A(A),
        .B(B),
        .GT(GT),
        .LT(LT),
        .EQ(EQ)
    );

    initial begin

        $dumpfile("comp.vcd");
        $dumpvars(0, comptb);

        $display(" A   B  | GT LT EQ");
        $display("-------------------");

        A=2'b00; B=2'b00; #10;
        $display("%b  %b |  %b  %b  %b",A,B,GT,LT,EQ);

        A=2'b00; B=2'b01; #10;
        $display("%b  %b |  %b  %b  %b",A,B,GT,LT,EQ);

        A=2'b00; B=2'b10; #10;
        $display("%b  %b |  %b  %b  %b",A,B,GT,LT,EQ);

        A=2'b00; B=2'b11; #10;
        $display("%b  %b |  %b  %b  %b",A,B,GT,LT,EQ);

        A=2'b01; B=2'b00; #10;
        $display("%b  %b |  %b  %b  %b",A,B,GT,LT,EQ);

        A=2'b01; B=2'b01; #10;
        $display("%b  %b |  %b  %b  %b",A,B,GT,LT,EQ);

        A=2'b01; B=2'b10; #10;
        $display("%b  %b |  %b  %b  %b",A,B,GT,LT,EQ);

        A=2'b01; B=2'b11; #10;
        $display("%b  %b |  %b  %b  %b",A,B,GT,LT,EQ);

        A=2'b10; B=2'b00; #10;
        $display("%b  %b |  %b  %b  %b",A,B,GT,LT,EQ);

        A=2'b10; B=2'b01; #10;
        $display("%b  %b |  %b  %b  %b",A,B,GT,LT,EQ);

        A=2'b10; B=2'b10; #10;
        $display("%b  %b |  %b  %b  %b",A,B,GT,LT,EQ);

        A=2'b10; B=2'b11; #10;
        $display("%b  %b |  %b  %b  %b",A,B,GT,LT,EQ);

        A=2'b11; B=2'b00; #10;
        $display("%b  %b |  %b  %b  %b",A,B,GT,LT,EQ);

        A=2'b11; B=2'b01; #10;
        $display("%b  %b |  %b  %b  %b",A,B,GT,LT,EQ);

        A=2'b11; B=2'b10; #10;
        $display("%b  %b |  %b  %b  %b",A,B,GT,LT,EQ);

        A=2'b11; B=2'b11; #10;
        $display("%b  %b |  %b  %b  %b",A,B,GT,LT,EQ);

        $finish;

    end

endmodule

Day2/comparator/comp.vcd
$date
	Sat Jul 18 05:00:24 2026
$end
$version
	Icarus Verilog
$end
$timescale
	1s
$end
$scope module comptb $end
$var wire 1 ! LT $end
$var wire 1 " GT $end
$var wire 1 # EQ $end
$var reg 2 $ A [1:0] $end
$var reg 2 % B [1:0] $end
$scope module uut $end
$var wire 2 & A [1:0] $end
$var wire 2 ' B [1:0] $end
$var wire 1 # EQ $end
$var wire 1 " GT $end
$var wire 1 ! LT $end
$var wire 1 ( eq0 $end
$var wire 1 ) eq1 $end
$var wire 1 * gt0 $end
$var wire 1 + gt1 $end
$var wire 1 , lt0 $end
$var wire 1 - lt1 $end
$var wire 1 . nA0 $end
$var wire 1 / nA1 $end
$var wire 1 0 nB0 $end
$var wire 1 1 nB1 $end
$var wire 1 2 wgt $end
$var wire 1 3 wlt $end
$upscope $end
$upscope $end
$enddefinitions $end
$comment Show the parameter values. $end
$dumpall
$end
#0
$dumpvars
03
02
11
10
1/
1.
0-
0,
0+
0*
1)
1(
b0 '
b0 &
b0 %
b0 $
1#
0"
0!
$end
#10
1!
0#
13
00
0(
1,
b1 %
b1 '
#20
03
01
10
0)
1(
1-
0,
b10 %
b10 '
#30
00
0(
1,
b11 %
b11 '
#40
1"
12
1*
0!
11
10
1)
0-
0,
0.
b0 %
b0 '
b1 $
b1 &
#50
0"
02
0*
1#
00
1(
b1 %
b1 '
#60
1*
0#
1!
01
10
0)
0(
1-
b10 %
b10 '
#70
0*
00
1(
b11 %
b11 '
#80
1"
1+
0!
11
10
0-
0/
1.
b0 %
b0 '
b10 $
b10 &
#90
00
0(
1,
b1 %
b1 '
#100
0"
0+
1#
01
10
1)
1(
0,
b10 %
b10 '
#110
1!
0#
13
00
0(
1,
b11 %
b11 '
#120
1"
0!
1+
1*
03
11
10
0)
0,
0.
b0 %
b0 '
b11 $
b11 &
#130
0*
00
1(
b1 %
b1 '
#140
12
0+
1*
01
10
1)
0(
b10 %
b10 '
#150
0"
02
0*
1#
00
1(
b11 %
b11 '
